cdk_emrserverless_with_delta_lake/__init__.py
cdk_emrserverless_with_delta_lake/py.typed
cdk_emrserverless_with_delta_lake/_jsii/__init__.py
cdk_emrserverless_with_delta_lake/_jsii/cdk-emrserverless-with-delta-lake@2.0.831.jsii.tgz
cdk_emrserverless_with_delta_lake-2.0.831.dist-info/LICENSE
cdk_emrserverless_with_delta_lake-2.0.831.dist-info/METADATA
cdk_emrserverless_with_delta_lake-2.0.831.dist-info/WHEEL
cdk_emrserverless_with_delta_lake-2.0.831.dist-info/top_level.txt
cdk_emrserverless_with_delta_lake-2.0.831.dist-info/RECORD
